{
  "entries": [
    {
      "at": "2026-07-14T13:56:32+00:00",
      "item": "content_lswposts_month-1-day-8_story_bulk-1783435884930-7-s1",
      "platform": "facebook",
      "kind": "story",
      "ok": true,
      "post_id": "916339610836670"
    },
    {
      "at": "2026-07-14T13:56:32+00:00",
      "item": "content_lswposts_month-1-day-8_story_bulk-1783435884930-7-s1",
      "platform": "instagram",
      "kind": "story",
      "ok": true,
      "post_id": "18270962845293230"
    },
    {
      "at": "2026-07-14T10:18:00+00:00",
      "item": "content_lswposts_month-1-day-8_feed_bulk-1783435884930-7-p1",
      "platform": "facebook",
      "kind": "image",
      "ok": true,
      "post_id": "1335681619620994_122110270983379104"
    },
    {
      "at": "2026-07-14T10:18:00+00:00",
      "item": "content_lswposts_month-1-day-8_feed_bulk-1783435884930-7-p1",
      "platform": "instagram",
      "kind": "image",
      "ok": true,
      "post_id": "17936640681311869"
    },
    {
      "at": "2026-07-14T08:22:57+00:00",
      "item": "content_lswposts_month-1-day-8_story_bulk-1783435884930-7-s0",
      "platform": "facebook",
      "kind": "story",
      "ok": true,
      "post_id": "4346324572298515"
    },
    {
      "at": "2026-07-14T08:22:57+00:00",
      "item": "content_lswposts_month-1-day-8_story_bulk-1783435884930-7-s0",
      "platform": "instagram",
      "kind": "story",
      "ok": true,
      "post_id": "18137035849602531"
    },
    {
      "at": "2026-07-14T08:22:57+00:00",
      "item": "content_lswposts_month-1-day-8_feed_bulk-1783435884930-7-p0",
      "platform": "facebook",
      "kind": "image",
      "ok": true,
      "post_id": "1335681619620994_122110210599379104"
    },
    {
      "at": "2026-07-14T08:22:57+00:00",
      "item": "content_lswposts_month-1-day-8_feed_bulk-1783435884930-7-p0",
      "platform": "instagram",
      "kind": "image",
      "ok": true,
      "post_id": "18131269225541652"
    },
    {
      "at": "2026-07-13T18:02:17+00:00",
      "item": "content_lswposts_month-1-day-7_story_bulk-1783435884930-6-s2",
      "platform": "facebook",
      "kind": "story",
      "ok": true,
      "post_id": "1069964995432275"
    },
    {
      "at": "2026-07-13T18:02:17+00:00",
      "item": "content_lswposts_month-1-day-7_story_bulk-1783435884930-6-s2",
      "platform": "instagram",
      "kind": "story",
      "ok": true,
      "post_id": "18124562251670629"
    },
    {
      "at": "2026-07-13T15:58:11+00:00",
      "item": "content_lswposts_month-1-day-7_feed_bulk-1783435884930-6-p2",
      "platform": "facebook",
      "kind": "image",
      "ok": true,
      "post_id": "1335681619620994_122109931317379104"
    },
    {
      "at": "2026-07-13T15:58:11+00:00",
      "item": "content_lswposts_month-1-day-7_feed_bulk-1783435884930-6-p2",
      "platform": "instagram",
      "kind": "image",
      "ok": true,
      "post_id": "17975688243061216"
    },
    {
      "at": "2026-07-13T13:06:35+00:00",
      "item": "content_lswposts_month-1-day-7_story_bulk-1783435884930-6-s1",
      "platform": "facebook",
      "kind": "story",
      "ok": true,
      "post_id": "1409769271251877"
    },
    {
      "at": "2026-07-13T13:06:35+00:00",
      "item": "content_lswposts_month-1-day-7_story_bulk-1783435884930-6-s1",
      "platform": "instagram",
      "kind": "story",
      "ok": true,
      "post_id": "18150771790507290"
    },
    {
      "at": "2026-07-13T10:34:02+00:00",
      "item": "content_lswposts_month-1-day-7_feed_bulk-1783435884930-6-p1",
      "platform": "facebook",
      "kind": "image",
      "ok": true,
      "post_id": "1335681619620994_122109817779379104"
    },
    {
      "at": "2026-07-13T10:34:02+00:00",
      "item": "content_lswposts_month-1-day-7_feed_bulk-1783435884930-6-p1",
      "platform": "instagram",
      "kind": "image",
      "ok": true,
      "post_id": "18187892836379420"
    },
    {
      "at": "2026-07-13T10:34:02+00:00",
      "item": "content_lswposts_month-1-day-7_story_bulk-1783435884930-6-s0",
      "platform": "facebook",
      "kind": "story",
      "ok": true,
      "post_id": "4537960979781464"
    },
    {
      "at": "2026-07-13T10:34:02+00:00",
      "item": "content_lswposts_month-1-day-7_story_bulk-1783435884930-6-s0",
      "platform": "instagram",
      "kind": "story",
      "ok": true,
      "post_id": "18069883517415044"
    },
    {
      "at": "2026-07-13T06:57:59+00:00",
      "item": "content_lswposts_month-1-day-7_feed_bulk-1783435884930-6-p0",
      "platform": "facebook",
      "kind": "image",
      "ok": true,
      "post_id": "1335681619620994_122109746409379104"
    },
    {
      "at": "2026-07-13T06:57:59+00:00",
      "item": "content_lswposts_month-1-day-7_feed_bulk-1783435884930-6-p0",
      "platform": "instagram",
      "kind": "image",
      "ok": true,
      "post_id": "17885437863434928"
    },
    {
      "at": "2026-07-12T16:36:29+00:00",
      "item": "content_lswposts_month-1-day-6_story_bulk-1783435884930-5-s2",
      "platform": "facebook",
      "kind": "story",
      "ok": true,
      "post_id": "1545346670709481"
    },
    {
      "at": "2026-07-12T16:36:29+00:00",
      "item": "content_lswposts_month-1-day-6_story_bulk-1783435884930-5-s2",
      "platform": "instagram",
      "kind": "story",
      "ok": true,
      "post_id": "18042550907802801"
    },
    {
      "at": "2026-07-12T14:16:59+00:00",
      "item": "content_lswposts_month-1-day-6_feed_bulk-1783435884930-5-p2",
      "platform": "facebook",
      "kind": "image",
      "ok": true,
      "post_id": "1335681619620994_122109552951379104"
    },
    {
      "at": "2026-07-12T14:16:59+00:00",
      "item": "content_lswposts_month-1-day-6_feed_bulk-1783435884930-5-p2",
      "platform": "instagram",
      "kind": "image",
      "ok": true,
      "post_id": "18108570283954944"
    },
    {
      "at": "2026-07-12T12:41:52+00:00",
      "item": "content_lswposts_month-1-day-6_story_bulk-1783435884930-5-s1",
      "platform": "facebook",
      "kind": "story",
      "ok": true,
      "post_id": "27506725318980924"
    },
    {
      "at": "2026-07-12T12:41:52+00:00",
      "item": "content_lswposts_month-1-day-6_story_bulk-1783435884930-5-s1",
      "platform": "instagram",
      "kind": "story",
      "ok": true,
      "post_id": "17967500456935237"
    },
    {
      "at": "2026-07-12T10:37:46+00:00",
      "item": "content_lswposts_month-1-day-6_feed_bulk-1783435884930-5-p1",
      "platform": "facebook",
      "kind": "image",
      "ok": true,
      "post_id": "1335681619620994_122109499491379104"
    },
    {
      "at": "2026-07-12T10:37:46+00:00",
      "item": "content_lswposts_month-1-day-6_feed_bulk-1783435884930-5-p1",
      "platform": "instagram",
      "kind": "image",
      "ok": true,
      "post_id": "18122478538815033"
    },
    {
      "at": "2026-07-12T08:54:43+00:00",
      "item": "content_lswposts_month-1-day-6_story_bulk-1783435884930-5-s0",
      "platform": "facebook",
      "kind": "story",
      "ok": true,
      "post_id": "1504084277580980"
    },
    {
      "at": "2026-07-12T08:54:43+00:00",
      "item": "content_lswposts_month-1-day-6_story_bulk-1783435884930-5-s0",
      "platform": "instagram",
      "kind": "story",
      "ok": true,
      "post_id": "18069946436449457"
    },
    {
      "at": "2026-07-12T06:37:25+00:00",
      "item": "content_lswposts_month-1-day-6_feed_bulk-1783435884930-5-p0",
      "platform": "facebook",
      "kind": "image",
      "ok": true,
      "post_id": "1335681619620994_122109439221379104"
    },
    {
      "at": "2026-07-12T06:37:25+00:00",
      "item": "content_lswposts_month-1-day-6_feed_bulk-1783435884930-5-p0",
      "platform": "instagram",
      "kind": "image",
      "ok": true,
      "post_id": "18116004578485378"
    },
    {
      "at": "2026-07-11T16:26:04+00:00",
      "item": "content_lswposts_month-1-day-5_story_bulk-1783435884930-4-s2",
      "platform": "facebook",
      "kind": "story",
      "ok": true,
      "post_id": "1005231465607840"
    },
    {
      "at": "2026-07-11T16:26:04+00:00",
      "item": "content_lswposts_month-1-day-5_story_bulk-1783435884930-4-s2",
      "platform": "instagram",
      "kind": "story",
      "ok": true,
      "post_id": "18087640820129940"
    },
    {
      "at": "2026-07-11T14:05:19+00:00",
      "item": "content_lswposts_month-1-day-5_feed_bulk-1783435884930-4-p2",
      "platform": "facebook",
      "kind": "image",
      "ok": true,
      "post_id": "1335681619620994_122109234519379104"
    },
    {
      "at": "2026-07-11T14:05:19+00:00",
      "item": "content_lswposts_month-1-day-5_feed_bulk-1783435884930-4-p2",
      "platform": "instagram",
      "kind": "image",
      "ok": true,
      "post_id": "18092565989629035"
    },
    {
      "at": "2026-07-11T12:30:05+00:00",
      "item": "content_lswposts_month-1-day-5_story_bulk-1783435884930-4-s1",
      "platform": "facebook",
      "kind": "story",
      "ok": true,
      "post_id": "2377152396146878"
    },
    {
      "at": "2026-07-11T12:30:05+00:00",
      "item": "content_lswposts_month-1-day-5_story_bulk-1783435884930-4-s1",
      "platform": "instagram",
      "kind": "story",
      "ok": true,
      "post_id": "18109309894954949"
    },
    {
      "at": "2026-07-11T10:04:08+00:00",
      "item": "content_lswposts_month-1-day-5_feed_bulk-1783435884930-4-p1",
      "platform": "facebook",
      "kind": "image",
      "ok": true,
      "post_id": "1335681619620994_122109145779379104"
    },
    {
      "at": "2026-07-11T10:04:08+00:00",
      "item": "content_lswposts_month-1-day-5_feed_bulk-1783435884930-4-p1",
      "platform": "instagram",
      "kind": "image",
      "ok": true,
      "post_id": "18092167718628239"
    },
    {
      "at": "2026-07-11T08:30:09+00:00",
      "item": "content_lswposts_month-1-day-5_story_bulk-1783435884930-4-s0",
      "platform": "facebook",
      "kind": "story",
      "ok": true,
      "post_id": "2811911749165471"
    },
    {
      "at": "2026-07-11T08:30:09+00:00",
      "item": "content_lswposts_month-1-day-5_story_bulk-1783435884930-4-s0",
      "platform": "instagram",
      "kind": "story",
      "ok": true,
      "post_id": "17919906789185691"
    },
    {
      "at": "2026-07-11T06:39:16+00:00",
      "item": "content_lswposts_month-1-day-5_feed_bulk-1783435884930-4-p0",
      "platform": "facebook",
      "kind": "image",
      "ok": true,
      "post_id": "1335681619620994_122109091635379104"
    },
    {
      "at": "2026-07-11T06:39:16+00:00",
      "item": "content_lswposts_month-1-day-5_feed_bulk-1783435884930-4-p0",
      "platform": "instagram",
      "kind": "image",
      "ok": true,
      "post_id": "18217424581329925"
    },
    {
      "at": "2026-07-10T16:48:00+00:00",
      "item": "content_lswposts_month-1-day-4_story_bulk-1783435884930-3-s2",
      "platform": "facebook",
      "kind": "story",
      "ok": true,
      "post_id": "1810205650358196"
    },
    {
      "at": "2026-07-10T16:48:00+00:00",
      "item": "content_lswposts_month-1-day-4_story_bulk-1783435884930-3-s2",
      "platform": "instagram",
      "kind": "story",
      "ok": true,
      "post_id": "17857355925675970"
    },
    {
      "at": "2026-07-10T14:37:35+00:00",
      "item": "content_lswposts_month-1-day-4_feed_bulk-1783435884930-3-p2",
      "platform": "facebook",
      "kind": "image",
      "ok": true,
      "post_id": "1335681619620994_122108815155379104"
    },
    {
      "at": "2026-07-10T14:37:35+00:00",
      "item": "content_lswposts_month-1-day-4_feed_bulk-1783435884930-3-p2",
      "platform": "instagram",
      "kind": "image",
      "ok": true,
      "post_id": "18108528025801851"
    },
    {
      "at": "2026-07-10T14:37:35+00:00",
      "item": "content_lswposts_month-1-day-4_story_bulk-1783435884930-3-s1",
      "platform": "facebook",
      "kind": "story",
      "ok": true,
      "post_id": "1337121317997534"
    },
    {
      "at": "2026-07-10T14:37:35+00:00",
      "item": "content_lswposts_month-1-day-4_story_bulk-1783435884930-3-s1",
      "platform": "instagram",
      "kind": "story",
      "ok": true,
      "post_id": "18540989683072610"
    },
    {
      "at": "2026-07-10T11:55:34+00:00",
      "item": "content_lswposts_month-1-day-4_feed_bulk-1783435884930-3-p1",
      "platform": "facebook",
      "kind": "image",
      "ok": true,
      "post_id": "1335681619620994_122108748045379104"
    },
    {
      "at": "2026-07-10T11:55:34+00:00",
      "item": "content_lswposts_month-1-day-4_feed_bulk-1783435884930-3-p1",
      "platform": "instagram",
      "kind": "image",
      "ok": true,
      "post_id": "17985033750009913"
    },
    {
      "at": "2026-07-10T08:51:26+00:00",
      "item": "content_lswposts_month-1-day-4_story_bulk-1783435884930-3-s0",
      "platform": "facebook",
      "kind": "story",
      "ok": true,
      "post_id": "1556241995903886"
    },
    {
      "at": "2026-07-10T08:51:26+00:00",
      "item": "content_lswposts_month-1-day-4_story_bulk-1783435884930-3-s0",
      "platform": "instagram",
      "kind": "story",
      "ok": true,
      "post_id": "18140937793543512"
    },
    {
      "at": "2026-07-10T08:51:26+00:00",
      "item": "content_lswposts_month-1-day-4_feed_bulk-1783435884930-3-p0",
      "platform": "facebook",
      "kind": "image",
      "ok": true,
      "post_id": "1335681619620994_122108562237379104"
    },
    {
      "at": "2026-07-10T08:51:26+00:00",
      "item": "content_lswposts_month-1-day-4_feed_bulk-1783435884930-3-p0",
      "platform": "instagram",
      "kind": "image",
      "ok": true,
      "post_id": "18104636722928316"
    },
    {
      "at": "2026-07-09T16:42:36+00:00",
      "item": "content_lswposts_month-1-day-3_story_bulk-1783435884930-2-s2",
      "platform": "facebook",
      "kind": "story",
      "ok": true,
      "post_id": "1828014908173251"
    },
    {
      "at": "2026-07-09T16:42:36+00:00",
      "item": "content_lswposts_month-1-day-3_story_bulk-1783435884930-2-s2",
      "platform": "instagram",
      "kind": "story",
      "ok": true,
      "post_id": "18016094099937093"
    },
    {
      "at": "2026-07-09T14:06:21+00:00",
      "item": "content_lswposts_month-1-day-3_feed_bulk-1783435884930-2-p2",
      "platform": "facebook",
      "kind": "image",
      "ok": true,
      "post_id": "1335681619620994_122108257251379104"
    },
    {
      "at": "2026-07-09T14:06:21+00:00",
      "item": "content_lswposts_month-1-day-3_feed_bulk-1783435884930-2-p2",
      "platform": "instagram",
      "kind": "image",
      "ok": true,
      "post_id": "18137617705565943"
    },
    {
      "at": "2026-07-09T14:06:21+00:00",
      "item": "content_lswposts_month-1-day-3_story_bulk-1783435884930-2-s1",
      "platform": "facebook",
      "kind": "story",
      "ok": true,
      "post_id": "3117164255160736"
    },
    {
      "at": "2026-07-09T14:06:21+00:00",
      "item": "content_lswposts_month-1-day-3_story_bulk-1783435884930-2-s1",
      "platform": "instagram",
      "kind": "story",
      "ok": true,
      "post_id": "17968087250932420"
    },
    {
      "at": "2026-07-09T11:20:08+00:00",
      "item": "content_lswposts_month-1-day-3_feed_bulk-1783435884930-2-p1",
      "platform": "facebook",
      "kind": "image",
      "ok": true,
      "post_id": "1335681619620994_122108214915379104"
    },
    {
      "at": "2026-07-09T11:20:08+00:00",
      "item": "content_lswposts_month-1-day-3_feed_bulk-1783435884930-2-p1",
      "platform": "instagram",
      "kind": "image",
      "ok": true,
      "post_id": "18062097917724620"
    },
    {
      "at": "2026-07-09T08:01:20+00:00",
      "item": "content_lswposts_month-1-day-3_story_bulk-1783435884930-2-s0",
      "platform": "facebook",
      "kind": "story",
      "ok": true,
      "post_id": "3509123005933143"
    },
    {
      "at": "2026-07-09T08:01:20+00:00",
      "item": "content_lswposts_month-1-day-3_story_bulk-1783435884930-2-s0",
      "platform": "instagram",
      "kind": "story",
      "ok": true,
      "post_id": "18087534356408160"
    },
    {
      "at": "2026-07-09T08:01:20+00:00",
      "item": "content_lswposts_month-1-day-3_feed_bulk-1783435884930-2-p0",
      "platform": "facebook",
      "kind": "image",
      "ok": true,
      "post_id": "1335681619620994_122108144961379104"
    },
    {
      "at": "2026-07-09T08:01:20+00:00",
      "item": "content_lswposts_month-1-day-3_feed_bulk-1783435884930-2-p0",
      "platform": "instagram",
      "kind": "image",
      "ok": true,
      "post_id": "17896276038349801"
    },
    {
      "at": "2026-07-08T17:11:15+00:00",
      "item": "content_lswposts_month-1-day-2_story_bulk-1783435884930-1-s2",
      "platform": "facebook",
      "kind": "story",
      "ok": true,
      "post_id": "1030570189568919"
    },
    {
      "at": "2026-07-08T17:11:15+00:00",
      "item": "content_lswposts_month-1-day-2_story_bulk-1783435884930-1-s2",
      "platform": "instagram",
      "kind": "story",
      "ok": true,
      "post_id": "18035071892816691"
    },
    {
      "at": "2026-07-08T15:35:58+00:00",
      "item": "content_lswposts_month-1-day-2_feed_bulk-1783435884930-1-p2",
      "platform": "facebook",
      "kind": "image",
      "ok": true,
      "post_id": "1335681619620994_122107814073379104"
    },
    {
      "at": "2026-07-08T15:35:58+00:00",
      "item": "content_lswposts_month-1-day-2_feed_bulk-1783435884930-1-p2",
      "platform": "instagram",
      "kind": "image",
      "ok": true,
      "post_id": "18088018385453270"
    },
    {
      "at": "2026-07-08T15:35:58+00:00",
      "item": "content_lswposts_month-1-day-2_story_bulk-1783435884930-1-s1",
      "platform": "facebook",
      "kind": "story",
      "ok": true,
      "post_id": "1563133718792694"
    },
    {
      "at": "2026-07-08T15:35:58+00:00",
      "item": "content_lswposts_month-1-day-2_story_bulk-1783435884930-1-s1",
      "platform": "instagram",
      "kind": "story",
      "ok": true,
      "post_id": "18361998472210646"
    },
    {
      "at": "2026-07-08T13:07:21+00:00",
      "item": "content_lswposts_month-1-day-2_feed_bulk-1783435884930-1-p1",
      "platform": "facebook",
      "kind": "image",
      "ok": true,
      "post_id": "1335681619620994_122107773255379104"
    },
    {
      "at": "2026-07-08T13:07:21+00:00",
      "item": "content_lswposts_month-1-day-2_feed_bulk-1783435884930-1-p1",
      "platform": "instagram",
      "kind": "image",
      "ok": true,
      "post_id": "18129445180627146"
    },
    {
      "at": "2026-07-08T11:19:45+00:00",
      "item": "content_lswposts_month-1-day-2_story_bulk-1783435884930-1-s0",
      "platform": "facebook",
      "kind": "story",
      "ok": true,
      "post_id": "1704105890737968"
    },
    {
      "at": "2026-07-08T11:19:45+00:00",
      "item": "content_lswposts_month-1-day-2_story_bulk-1783435884930-1-s0",
      "platform": "instagram",
      "kind": "story",
      "ok": true,
      "post_id": "17901790845303563"
    },
    {
      "at": "2026-07-08T09:14:58+00:00",
      "item": "content_lswposts_month-1-day-2_feed_bulk-1783435884930-1-p0",
      "platform": "facebook",
      "kind": "image",
      "ok": true,
      "post_id": "1335681619620994_122107674069379104"
    },
    {
      "at": "2026-07-08T09:14:58+00:00",
      "item": "content_lswposts_month-1-day-2_feed_bulk-1783435884930-1-p0",
      "platform": "instagram",
      "kind": "image",
      "ok": true,
      "post_id": "18098441795589524"
    },
    {
      "at": "2026-07-08T09:14:58+00:00",
      "item": "content_lswposts_month-1-day-2_story_bulk-1783430153913-1-s0",
      "platform": "facebook",
      "kind": "story",
      "ok": true,
      "post_id": "1348458399952977"
    },
    {
      "at": "2026-07-08T09:14:58+00:00",
      "item": "content_lswposts_month-1-day-2_story_bulk-1783430153913-1-s0",
      "platform": "instagram",
      "kind": "story",
      "ok": true,
      "post_id": "17874055818619740"
    },
    {
      "at": "2026-07-08T06:31:23+00:00",
      "item": "content_lswposts_month-1-day-2_feed_bulk-1783430153913-1-p0",
      "platform": "facebook",
      "kind": "image",
      "ok": true,
      "post_id": "1335681619620994_122107597257379104"
    },
    {
      "at": "2026-07-08T06:31:23+00:00",
      "item": "content_lswposts_month-1-day-2_feed_bulk-1783430153913-1-p0",
      "platform": "instagram",
      "kind": "image",
      "ok": true,
      "post_id": "17945407296082401"
    },
    {
      "at": "2026-07-07T23:05:37+00:00",
      "item": "content_lswposts_month-1-day-1_story_bulk-1783435884930-0-s2",
      "platform": "facebook",
      "kind": "story",
      "ok": true,
      "post_id": "998229343117690"
    },
    {
      "at": "2026-07-07T23:05:37+00:00",
      "item": "content_lswposts_month-1-day-1_story_bulk-1783435884930-0-s2",
      "platform": "instagram",
      "kind": "story",
      "ok": true,
      "post_id": "18105866275827821"
    },
    {
      "at": "2026-07-07T21:54:26+00:00",
      "item": "content_lswposts_month-1-day-1_feed_bulk-1783435884930-0-p2",
      "platform": "facebook",
      "kind": "image",
      "ok": true,
      "post_id": "1335681619620994_122107423407379104"
    },
    {
      "at": "2026-07-07T21:54:26+00:00",
      "item": "content_lswposts_month-1-day-1_feed_bulk-1783435884930-0-p2",
      "platform": "instagram",
      "kind": "image",
      "ok": true,
      "post_id": "18102386608887798"
    },
    {
      "at": "2026-07-07T20:16:09+00:00",
      "item": "content_lswposts_month-1-day-1_story_bulk-1783435884930-0-s1",
      "platform": "facebook",
      "kind": "story",
      "ok": true,
      "post_id": "1052173567495333"
    },
    {
      "at": "2026-07-07T20:16:09+00:00",
      "item": "content_lswposts_month-1-day-1_story_bulk-1783435884930-0-s1",
      "platform": "instagram",
      "kind": "story",
      "ok": true,
      "post_id": "18063613199495455"
    },
    {
      "at": "2026-07-07T18:03:25+00:00",
      "item": "content_lswposts_month-1-day-1_feed_bulk-1783435884930-0-p1",
      "platform": "facebook",
      "kind": "image",
      "ok": true,
      "post_id": "1335681619620994_122107365867379104"
    },
    {
      "at": "2026-07-07T18:03:25+00:00",
      "item": "content_lswposts_month-1-day-1_feed_bulk-1783435884930-0-p1",
      "platform": "instagram",
      "kind": "image",
      "ok": true,
      "post_id": "18068718344709102"
    },
    {
      "at": "2026-07-07T17:09:40+00:00",
      "item": "content_lswposts_month-1-day-1_story_bulk-1783435884930-0-s0",
      "platform": "facebook",
      "kind": "story",
      "ok": true,
      "post_id": "1386495663325186"
    },
    {
      "at": "2026-07-07T17:09:40+00:00",
      "item": "content_lswposts_month-1-day-1_story_bulk-1783435884930-0-s0",
      "platform": "instagram",
      "kind": "story",
      "ok": true,
      "post_id": "18080516933250411"
    },
    {
      "at": "2026-07-07T15:39:21+00:00",
      "item": "content_lswposts_month-1-day-1_feed_bulk-1783435884930-0-p0",
      "platform": "facebook",
      "kind": "image",
      "ok": true,
      "post_id": "1335681619620994_122107324149379104"
    },
    {
      "at": "2026-07-07T15:39:21+00:00",
      "item": "content_lswposts_month-1-day-1_feed_bulk-1783435884930-0-p0",
      "platform": "instagram",
      "kind": "image",
      "ok": true,
      "post_id": "18099871154250614"
    },
    {
      "at": "2026-07-07T15:39:21+00:00",
      "item": "content_lswposts_month-1-day-1_story_bulk-1783430153913-0-s2",
      "platform": "facebook",
      "kind": "story",
      "ok": true,
      "post_id": "2102961827321899"
    },
    {
      "at": "2026-07-07T15:39:21+00:00",
      "item": "content_lswposts_month-1-day-1_story_bulk-1783430153913-0-s2",
      "platform": "instagram",
      "kind": "story",
      "ok": true,
      "post_id": "17878730646674128"
    },
    {
      "at": "2026-07-07T15:39:21+00:00",
      "item": "content_lswposts_month-1-day-1_feed_bulk-1783430153913-0-p2",
      "platform": "facebook",
      "kind": "image",
      "ok": true,
      "post_id": "1335681619620994_122107323723379104"
    },
    {
      "at": "2026-07-07T15:39:21+00:00",
      "item": "content_lswposts_month-1-day-1_feed_bulk-1783430153913-0-p2",
      "platform": "instagram",
      "kind": "image",
      "ok": true,
      "post_id": "17887644423418640"
    },
    {
      "at": "2026-07-07T15:39:21+00:00",
      "item": "content_lswposts_month-1-day-1_story_bulk-1783430153913-0-s1",
      "platform": "facebook",
      "kind": "story",
      "ok": true,
      "post_id": "37608762285373877"
    },
    {
      "at": "2026-07-07T15:39:21+00:00",
      "item": "content_lswposts_month-1-day-1_story_bulk-1783430153913-0-s1",
      "platform": "instagram",
      "kind": "story",
      "ok": true,
      "post_id": "18019804157902225"
    },
    {
      "at": "2026-07-07T15:39:21+00:00",
      "item": "content_lswposts_month-1-day-1_feed_bulk-1783430153913-0-p1",
      "platform": "facebook",
      "kind": "image",
      "ok": true,
      "post_id": "1335681619620994_122107323135379104"
    },
    {
      "at": "2026-07-07T15:39:21+00:00",
      "item": "content_lswposts_month-1-day-1_feed_bulk-1783430153913-0-p1",
      "platform": "instagram",
      "kind": "image",
      "ok": true,
      "post_id": "18097779137253004"
    },
    {
      "at": "2026-07-07T15:39:21+00:00",
      "item": "content_lswposts_month-1-day-1_story_bulk-1783430153913-0-s0",
      "platform": "facebook",
      "kind": "story",
      "ok": true,
      "post_id": "1388628979855419"
    },
    {
      "at": "2026-07-07T15:39:21+00:00",
      "item": "content_lswposts_month-1-day-1_story_bulk-1783430153913-0-s0",
      "platform": "instagram",
      "kind": "story",
      "ok": true,
      "post_id": "17952376209188858"
    },
    {
      "at": "2026-07-07T15:39:21+00:00",
      "item": "content_lswposts_month-1-day-1_feed_bulk-1783430153913-0-p0",
      "platform": "facebook",
      "kind": "image",
      "ok": true,
      "post_id": "1335681619620994_122107322727379104"
    },
    {
      "at": "2026-07-07T15:39:21+00:00",
      "item": "content_lswposts_month-1-day-1_feed_bulk-1783430153913-0-p0",
      "platform": "instagram",
      "kind": "image",
      "ok": true,
      "post_id": "18095974307370768"
    }
  ]
}
