[
  {
    "timestamp": "2026-07-07T15:17:00+00:00",
    "topic": "a common customer question, answered",
    "results": {
      "facebook": "ok:1335681619620994_122107315077379104"
    }
  },
  {
    "timestamp": "2026-07-07T15:36:08+00:00",
    "topic": "what makes our products and service stand out",
    "results": {
      "facebook": "ok:1335681619620994_122107321863379104"
    }
  },
  {
    "timestamp": "2026-07-08T10:55:43+00:00",
    "topic": "a look at our latest work",
    "results": {
      "facebook": "ok:1335681619620994_122107729587379104"
    }
  },
  {
    "timestamp": "2026-07-10T11:44:11+00:00",
    "topic": "why quality matters and saves money long term",
    "results": {
      "facebook": "ok:1335681619620994_122108741091379104"
    }
  },
  {
    "timestamp": "2026-07-13T11:53:44+00:00",
    "topic": "a common customer question, answered",
    "results": {
      "facebook": "ok:1335681619620994_122109869529379104"
    }
  },
  {
    "timestamp": "2026-07-15T10:42:54+00:00",
    "topic": "what makes our products and service stand out",
    "results": {
      "facebook": "ok:1335681619620994_122110658127379104"
    }
  },
  {
    "timestamp": "2026-07-17T10:39:31+00:00",
    "topic": "a look at our latest work",
    "results": {
      "facebook": "ok:1335681619620994_122111241363379104"
    }
  },
  {
    "timestamp": "2026-07-20T11:37:33+00:00",
    "topic": "why quality matters and saves money long term",
    "results": {
      "facebook": "ok:1335681619620994_122112020301379104"
    }
  },
  {
    "timestamp": "2026-07-22T10:59:49+00:00",
    "topic": "a common customer question, answered",
    "results": {
      "facebook": "ok:1335681619620994_122112498663379104"
    }
  },
  {
    "timestamp": "2026-07-24T10:55:22+00:00",
    "topic": "what makes our products and service stand out",
    "results": {
      "facebook": "ok:1335681619620994_122113000233379104"
    }
  }
]